LICENSE
datetime_helpers/__init__.py
datetime_helpers/py.typed
datetime_helpers/utils.py
datetime_helpers-0.0.14.dist-info/LICENSE
datetime_helpers-0.0.14.dist-info/WHEEL
datetime_helpers-0.0.14.dist-info/METADATA
datetime_helpers-0.0.14.dist-info/RECORD
